Opencv2JisuanjiShijueYingyongBianchengMijiChuyiFix1/README.md
Opencv2JisuanjiShijueYingyongBianchengMijiChuyiFix1/__init__.py
Opencv2JisuanjiShijueYingyongBianchengMijiChuyiFix1/__main__.py
Opencv2JisuanjiShijueYingyongBianchengMijiChuyiFix1/file.epub
Opencv2JisuanjiShijueYingyongBianchengMijiChuyiFix1/index.html
Opencv2JisuanjiShijueYingyongBianchengMijiChuyiFix1/css/__init__.py
Opencv2JisuanjiShijueYingyongBianchengMijiChuyiFix1/css/annotations.css
Opencv2JisuanjiShijueYingyongBianchengMijiChuyiFix1/css/main.css
Opencv2JisuanjiShijueYingyongBianchengMijiChuyiFix1/css/normalize.css
Opencv2JisuanjiShijueYingyongBianchengMijiChuyiFix1/css/popup.css
Opencv2JisuanjiShijueYingyongBianchengMijiChuyiFix1/font/__init__.py
Opencv2JisuanjiShijueYingyongBianchengMijiChuyiFix1/font/fontello.eot
Opencv2JisuanjiShijueYingyongBianchengMijiChuyiFix1/font/fontello.svg
Opencv2JisuanjiShijueYingyongBianchengMijiChuyiFix1/font/fontello.ttf
Opencv2JisuanjiShijueYingyongBianchengMijiChuyiFix1/font/fontello.woff
Opencv2JisuanjiShijueYingyongBianchengMijiChuyiFix1/img/__init__.py
Opencv2JisuanjiShijueYingyongBianchengMijiChuyiFix1/img/annotator-glyph-sprite.png
Opencv2JisuanjiShijueYingyongBianchengMijiChuyiFix1/img/annotator-icon-sprite.png
Opencv2JisuanjiShijueYingyongBianchengMijiChuyiFix1/img/apple-touch-icon.png
Opencv2JisuanjiShijueYingyongBianchengMijiChuyiFix1/img/cancelfullscreen.png
Opencv2JisuanjiShijueYingyongBianchengMijiChuyiFix1/img/close.png
Opencv2JisuanjiShijueYingyongBianchengMijiChuyiFix1/img/fullscreen.png
Opencv2JisuanjiShijueYingyongBianchengMijiChuyiFix1/img/loader.gif
Opencv2JisuanjiShijueYingyongBianchengMijiChuyiFix1/img/menu-icon.png
Opencv2JisuanjiShijueYingyongBianchengMijiChuyiFix1/img/save.png
Opencv2JisuanjiShijueYingyongBianchengMijiChuyiFix1/img/saved.png
Opencv2JisuanjiShijueYingyongBianchengMijiChuyiFix1/img/settings-s.png
Opencv2JisuanjiShijueYingyongBianchengMijiChuyiFix1/img/settings.png
opencv2_jisuanji_shijue_yingyong_biancheng_miji_chuyi_fix1-2025.3.25.1.dist-info/METADATA
opencv2_jisuanji_shijue_yingyong_biancheng_miji_chuyi_fix1-2025.3.25.1.dist-info/WHEEL
opencv2_jisuanji_shijue_yingyong_biancheng_miji_chuyi_fix1-2025.3.25.1.dist-info/entry_points.txt
opencv2_jisuanji_shijue_yingyong_biancheng_miji_chuyi_fix1-2025.3.25.1.dist-info/top_level.txt
opencv2_jisuanji_shijue_yingyong_biancheng_miji_chuyi_fix1-2025.3.25.1.dist-info/RECORD
